[{"company":"American Century NT Diversified Bond I","symbol":"N/A","percent":"25.91","return":"N/A"},{"company":"American Century NT Large Company Val I","symbol":"N/A","percent":"11.15","return":"N/A"},{"company":"American Century NT Equity Growth Instl","symbol":"N/A","percent":"9.85","return":"N/A"},{"company":"American Century Infl-Adj Bond Instl","symbol":"N/A","percent":"7.54","return":"N/A"},{"company":"American Century NT Growth Institutional","symbol":"N/A","percent":"7.13","return":"N/A"},{"company":"American Century International Bd Instl","symbol":"N/A","percent":"6.42","return":"N/A"},{"company":"American Century NT Intl Growth I","symbol":"N/A","percent":"5.46","return":"N/A"},{"company":"American Century NT Mid Cap Value I","symbol":"N/A","percent":"4.38","return":"N/A"},{"company":"American Century High-Yield Instl","symbol":"N/A","percent":"3.76","return":"N/A"},{"company":"American Century NT Core Eq Pls Instl","symbol":"N/A","percent":"2.99","return":"N/A"}]