[{"company":"Fannie Mae Single Family TBA 2.5% 2027-09-01","symbol":"N/A","percent":"12.55","return":"N/A"},{"company":"Fannie Mae Single Family TBA 4% 2042-09-01","symbol":"N/A","percent":"4.61","return":"N/A"},{"company":"Fannie Mae Single Family TBA 3% 2042-09-01","symbol":"N/A","percent":"4.44","return":"N/A"},{"company":"Fannie Mae Single Family TBA 3% 2027-09-01","symbol":"N/A","percent":"3.82","return":"N/A"},{"company":"Fannie Mae Single Family TBA 5% 2042-10-01","symbol":"N/A","percent":"3.34","return":"N/A"},{"company":"Fannie Mae Single Family TBA 5.5% 2042-10-01","symbol":"N/A","percent":"2.54","return":"N/A"},{"company":"FNMA 4%","symbol":"N/A","percent":"2.29","return":"N/A"},{"company":"Fannie Mae Single Family TBA 4.5% 2042-09-01","symbol":"N/A","percent":"2.28","return":"N/A"},{"company":"Freddie Mac Gold Single Family TBA 5% 2042-09-01","symbol":"N/A","percent":"2.28","return":"N/A"},{"company":"Freddie Mac Gold Single Family TBA 2.5% 2027-09-01","symbol":"N/A","percent":"2.15","return":"N/A"}]