[{"company":"E.ON Aktiengesellschaft AG","symbol":"ENAKF.DE","percent":"7.73","return":"National Grid PLC"},{"company":"NGGTF.L","symbol":"6.95","percent":"GDF SUEZ","return":"GSZ.PA"},{"company":"5.14","symbol":"Centrica PLC","percent":"CPYYF.L","return":"4.91"},{"company":"ENEL Ente Nazionale per L'Energ Elet SPA","symbol":"ESOCF.MI","percent":"4.18","return":"RWE"},{"company":"RWE.DE","symbol":"4.02","percent":"SSE Plc.","return":"SSEZF.L"},{"company":"3.78","symbol":"Iberdrola SA","percent":"IBE.BC","return":"3.26"},{"company":"CLP Holdings Limited","symbol":"CLPHF.HK","percent":"3.07","return":"Hong Kong and China Gas Co., Ltd."},{"company":"00003.HK","symbol":"2.58","percent":null,"return":null}]