[{"company":"Pfizer, Inc. Common Stock","symbol":"PFE","percent":"4.36","return":"18.74"},{"company":"Chevron Corporation Common Stoc","symbol":"CVX","percent":"4.32","return":"12.65"},{"company":"Merck & Company, Inc. Common St","symbol":"MRK","percent":"3.87","return":"23.28"},{"company":"Microsoft Corporation","symbol":"MSFT","percent":"3.84","return":"15.91"},{"company":"ConocoPhillips Common Stock","symbol":"COP","percent":"3.52","return":"6.63"},{"company":"The Travelers Companies, Inc. C","symbol":"TRV","percent":"3.42","return":"18.98"},{"company":"Johnson & Johnson Common Stock","symbol":"JNJ","percent":"3.21","return":"8.14"},{"company":"Pepsico, Inc. Common Stock","symbol":"PEP","percent":"3.12","return":"8.88"},{"company":"Intel Corporation","symbol":"INTC","percent":"2.55","return":"-3.51"},{"company":"3M Company Common Stock","symbol":"MMM","percent":"2.44","return":"16.31"}]