[{"company":"DXP Enterprises, Inc.","symbol":"DXPE","percent":"2.31","return":"39.01"},{"company":"Insight Enterprises, Inc.","symbol":"NSIT","percent":"2.03","return":"30.28"},{"company":"HealthStream, Inc.","symbol":"HSTM","percent":"1.89","return":"23.52"},{"company":"Select Comfort Corporation","symbol":"SCSS","percent":"1.78","return":"38.08"},{"company":"The Ensign Group, Inc.","symbol":"ENSG","percent":"1.69","return":"9.76"},{"company":"Standard Motor Products, Inc. C","symbol":"SMP","percent":"1.69","return":"-23.64"},{"company":"Temporary Invt Fd","symbol":"N/A","percent":"1.67","return":"65.43"},{"company":"Sturm, Ruger & Company, Inc. Co","symbol":"RGR","percent":"1.64","return":"1.76"},{"company":"Republic Bancorp, Inc.","symbol":"RBCAA","percent":"1.55","return":"61.00"},{"company":"On Assignment, Inc. Common Stoc","symbol":"ASGN","percent":"1.51","return":"N/A"}]