[{"company":"Apple Inc.","symbol":"AAPL","percent":"7.48","return":"63.47"},{"company":"Equinix, Inc.","symbol":"EQIX","percent":"6.03","return":"100.42"},{"company":"Humana Inc. Common Stock","symbol":"HUM","percent":"5.26","return":"-17.71"},{"company":"Liberty Media Corporation","symbol":"LMCA","percent":"4.24","return":"34.23"},{"company":"Mastercard Incorporated Common","symbol":"MA","percent":"3.22","return":"22.75"},{"company":"Amazon.com, Inc.","symbol":"AMZN","percent":"3.19","return":"45.59"},{"company":"Vail Resorts, Inc. Common Stock","symbol":"MTN","percent":"3.18","return":"37.62"},{"company":"DIRECTV","symbol":"DTV","percent":"3.10","return":"21.69"},{"company":"Acacia Research Corporation","symbol":"ACTG","percent":"2.99","return":"-27.72"},{"company":"Anadarko Petroleum Corporation","symbol":"APC","percent":"2.84","return":"-7.13"}]