[{"company":"Ontario Prov Cda 4.4%","symbol":"N/A","percent":"4.80","return":"N/A"},{"company":"United Kingdom (Government Of) 4.5%","symbol":"N/A","percent":"4.50","return":"N/A"},{"company":"Poland(Rep Of) 5.5%","symbol":"N/A","percent":"3.76","return":"N/A"},{"company":"Sweden(Kingdom Of) 3.75%","symbol":"N/A","percent":"3.67","return":"N/A"},{"company":"France(Govt Of) 2.5%","symbol":"N/A","percent":"3.57","return":"N/A"},{"company":"Germany (Federal Republic Of) 3.25%","symbol":"N/A","percent":"3.53","return":"N/A"},{"company":"Japan(Govt Of) 1.1%","symbol":"N/A","percent":"2.99","return":"N/A"},{"company":"Netherlands (Kingdom of) 4%","symbol":"N/A","percent":"2.86","return":"N/A"},{"company":"France(Govt Of) 2.25%","symbol":"N/A","percent":"2.79","return":"N/A"},{"company":"Mexico(Utd Mex St) 8.5%","symbol":"N/A","percent":"2.69","return":"N/A"}]