[{"company":"Westfield Group","symbol":"WEFIF.AX","percent":"8.62","return":"-16.89"},{"company":"UNIBAIL-RODAMCO","symbol":"UL.PA","percent":"6.76","return":"-1.13"},{"company":"Link Real Estate Investment Trust","symbol":"00823.HK","percent":"3.97","return":"N/A"},{"company":"LAND SEC R.E.I.T.","symbol":"LAND.L","percent":"3.76","return":"N/A"},{"company":"WESTFTRUST STAPLED","symbol":"WRT.AX","percent":"3.67","return":"N/A"},{"company":"Stockland Corporation Limited","symbol":"STKAF.AX","percent":"3.14","return":"N/A"},{"company":"BRIT LAND CO REIT","symbol":"BLND.L","percent":"2.73","return":"N/A"},{"company":"GPT STAPLED","symbol":"GPT.AX","percent":"2.43","return":"N/A"},{"company":"GOOD GROUP FORUS","symbol":"GMG.AX","percent":"2.40","return":"N/A"},{"company":"Nippon Building Fund Inc","symbol":"8951","percent":"2.39","return":"N/A"}]