[{"company":"Extra Space Storage Inc Common","symbol":"EXR","percent":"0.72","return":"38.38"},{"company":"Kilroy Realty Corporation Commo","symbol":"KRC","percent":"0.65","return":"19.83"},{"company":"Tanger Factory Outlet Centers,","symbol":"SKT","percent":"0.59","return":"10.57"},{"company":"The Hain Celestial Group, Inc.","symbol":"HAIN","percent":"0.59","return":"78.86"},{"company":"Post Properties, Inc. Common St","symbol":"PPS","percent":"0.58","return":"10.25"},{"company":"Robbins & Myers, Inc. Common St","symbol":"RBN","percent":"0.56","return":"23.42"},{"company":"ProAssurance Corporation Common","symbol":"PRA","percent":"0.55","return":"14.87"},{"company":"Questcor Pharmaceuticals, Inc.","symbol":"QCOR","percent":"0.55","return":"-54.28"},{"company":"Cubist Pharmaceuticals, Inc.","symbol":"CBST","percent":"0.55","return":"21.23"},{"company":"Mid-America Apartment Communiti","symbol":"MAA","percent":"0.54","return":"5.71"}]