[{"company":"International Business Machines","symbol":"IBM","percent":"3.12","return":"7.13"},{"company":"McDonald's Corporation Common S","symbol":"MCD","percent":"2.54","return":"-9.15"},{"company":"PNC Financial Services Group, I","symbol":"PNC","percent":"2.54","return":"10.09"},{"company":"U.S. Bancorp Common Stock","symbol":"USB","percent":"2.51","return":"23.88"},{"company":"TJX Companies, Inc. (The) Commo","symbol":"TJX","percent":"2.43","return":"44.32"},{"company":"Covidien plc. Ordinary Shares (","symbol":"COV","percent":"2.35","return":"26.49"},{"company":"SANOFI","symbol":"SAN.PA","percent":"2.34","return":"15.98"},{"company":"Accenture plc. Class A Ordinary","symbol":"ACN","percent":"2.23","return":"-3.21"},{"company":"VINCI","symbol":"DG.PA","percent":"2.19","return":"N/A"},{"company":"Royal Dutch Shell PLC Class A","symbol":"RYDAF.L","percent":"2.10","return":"N/A"}]