[{"company":"QUALCOMM Incorporated","symbol":"QCOM","percent":"6.60","return":"14.88"},{"company":"Visa Inc.","symbol":"V","percent":"6.54","return":"35.54"},{"company":"Celgene Corporation","symbol":"CELG","percent":"6.18","return":"13.58"},{"company":"Cognizant Technology Solutions","symbol":"CTSH","percent":"5.91","return":"10.79"},{"company":"Apple Inc.","symbol":"AAPL","percent":"5.38","return":"63.47"},{"company":"Amazon.com, Inc.","symbol":"AMZN","percent":"5.14","return":"45.59"},{"company":"Google Inc.","symbol":"GOOG","percent":"5.12","return":"17.94"},{"company":"CME Group Inc.","symbol":"CME","percent":"4.81","return":"21.15"},{"company":"American Tower Corporation (REI","symbol":"AMT","percent":"4.81","return":"19.53"},{"company":"T. Rowe Price Group, Inc.","symbol":"TROW","percent":"4.66","return":"12.75"}]