[{"company":"Simon Property Group, Inc. Comm","symbol":"SPG","percent":"10.89","return":"19.58"},{"company":"AvalonBay Communities, Inc. Com","symbol":"AVB","percent":"6.91","return":"5.92"},{"company":"Equity Residential Common Share","symbol":"EQR","percent":"6.62","return":"2.09"},{"company":"Boston Properties, Inc. Common","symbol":"BXP","percent":"6.61","return":"11.54"},{"company":"Public Storage Common Stock","symbol":"PSA","percent":"6.52","return":"5.80"},{"company":"Ventas, Inc. Common Stock","symbol":"VTR","percent":"3.66","return":"15.51"},{"company":"Federal Realty Investment Trust","symbol":"FRT","percent":"3.38","return":"18.17"},{"company":"Vornado Realty Trust Common Sto","symbol":"VNO","percent":"2.84","return":"7.16"},{"company":"Taubman Centers, Inc. Common St","symbol":"TCO","percent":"2.68","return":"24.60"},{"company":"Health Care REIT, Inc. Common S","symbol":"HCN","percent":"2.44","return":"9.54"}]