[{"company":"Utilities Select Sector SPDR","symbol":"N/A","percent":"15.77","return":"N/A"},{"company":"Consumer Staples Select Sector SPDR","symbol":"N/A","percent":"15.74","return":"N/A"},{"company":"Technology Select Sector SPDR","symbol":"N/A","percent":"15.71","return":"N/A"},{"company":"Industrial Select Sector SPDR","symbol":"N/A","percent":"15.64","return":"N/A"},{"company":"Health Care Select Sector SPDR","symbol":"N/A","percent":"15.63","return":"N/A"},{"company":"Financial Select Sector SPDR","symbol":"N/A","percent":"15.51","return":"N/A"},{"company":"Consumer Discret Select Sector SPDR","symbol":"N/A","percent":"15.41","return":"N/A"},{"company":"Materials Select Sector SPDR","symbol":"N/A","percent":"4.77","return":"N/A"},{"company":"Energy Select Sector SPDR","symbol":"N/A","percent":"4.49","return":"N/A"},{"company":"iShares Dow Jones US Energy","symbol":"N/A","percent":"0.48","return":"N/A"}]