[{"company":"E.I. du Pont de Nemours and Com","symbol":"DD","percent":"10.22","return":"Monsanto Company Common Stock"},{"company":"MON","symbol":"10.10","percent":"Freeport-McMoRan Copper & Gold,","return":"FCX"},{"company":"6.99","symbol":"Newmont Mining Corporation","percent":"NEM","return":"4.81"},{"company":"Mosaic Company (The) Common Sto","symbol":"MOS","percent":"3.80","return":"Ecolab Inc. Common Stock"},{"company":"ECL","symbol":"3.79","percent":"PPG Industries, Inc. Common Sto","return":"PPG"},{"company":"3.67","symbol":"Air Products and Chemicals, Inc","percent":"APD","return":"3.52"},{"company":"International Paper Company Com","symbol":"IP","percent":"2.92","return":"CF Industries Holdings, Inc. Co"},{"company":"CF","symbol":"2.83","percent":null,"return":null}]