[{"company":"Us Treasury 10yr Fut Sep12","symbol":"N/A","percent":"2.43","return":"N/A"},{"company":"FHLBA 1.375%","symbol":"N/A","percent":"1.72","return":"N/A"},{"company":"Citigroup 4.587%","symbol":"N/A","percent":"1.48","return":"N/A"},{"company":"FNMA 2.5%","symbol":"N/A","percent":"1.46","return":"N/A"},{"company":"Bk Amer Fdg 4.5%","symbol":"N/A","percent":"1.18","return":"N/A"},{"company":"Goldman Sachs Grp Inc Mtn Be 3.7%","symbol":"N/A","percent":"1.05","return":"N/A"},{"company":"Smart Us Tr 2011-1 FRN","symbol":"N/A","percent":"0.95","return":"N/A"},{"company":"Chase Issuance Tr 2012-3a 0.79%","symbol":"N/A","percent":"0.91","return":"N/A"},{"company":"Fannie Mae Single Family TBA 3% 2027-08-01","symbol":"N/A","percent":"0.89","return":"N/A"},{"company":"Gs Mtg Coml 2007-Gg10 5.993%","symbol":"N/A","percent":"0.89","return":"N/A"}]