[{"company":"Coinstar, Inc.","symbol":"CSTR","percent":"2.13","return":"-2.61"},{"company":"Peet's Coffee & Tea, Inc.","symbol":"PEET","percent":"1.81","return":"17.21"},{"company":"Allegiant Travel Company","symbol":"ALGT","percent":"1.71","return":"21.92"},{"company":"Boston Beer Company, Inc. (The)","symbol":"SAM","percent":"1.66","return":"0.48"},{"company":"PAREXEL International Corporati","symbol":"PRXL","percent":"1.58","return":"49.76"},{"company":"Grand Canyon Education, Inc.","symbol":"LOPE","percent":"1.55","return":"46.24"},{"company":"FARO Technologies, Inc.","symbol":"FARO","percent":"1.48","return":"-8.37"},{"company":"Treehouse Foods, Inc. Common St","symbol":"THS","percent":"1.48","return":"-18.95"},{"company":"Echo Global Logistics, Inc.","symbol":"ECHO","percent":"1.46","return":"9.29"},{"company":"Shutterfly, Inc.","symbol":"SFLY","percent":"1.44","return":"31.55"}]