[{"company":"Altria Group, Inc.","symbol":"MO","percent":"3.81","return":"17.71"},{"company":"Philip Morris International Inc","symbol":"PM","percent":"3.78","return":"18.63"},{"company":"AT&T Inc.","symbol":"T","percent":"3.76","return":"29.20"},{"company":"Merck & Company, Inc. Common St","symbol":"MRK","percent":"3.75","return":"23.28"},{"company":"General Electric Company Common","symbol":"GE","percent":"3.69","return":"30.21"},{"company":"Dr Pepper Snapple Group, Inc Dr","symbol":"DPS","percent":"3.56","return":"15.63"},{"company":"Raytheon Company Common Stock","symbol":"RTN","percent":"3.56","return":"17.98"},{"company":"Verizon Communications Inc. Com","symbol":"VZ","percent":"3.53","return":"17.92"},{"company":"Reynolds American Inc Common St","symbol":"RAI","percent":"3.51","return":"9.10"},{"company":"Pfizer, Inc. Common Stock","symbol":"PFE","percent":"3.49","return":"18.74"}]