[{"company":"Fidelity Series All-Sector Equity","symbol":"N/A","percent":"11.68","return":"N/A"},{"company":"Fidelity Series Large Cap Value","symbol":"N/A","percent":"9.90","return":"N/A"},{"company":"Fidelity Series Commodity Strategy","symbol":"N/A","percent":"9.46","return":"N/A"},{"company":"Fidelity Series Investment Grade Bond","symbol":"N/A","percent":"9.43","return":"N/A"},{"company":"Fidelity Growth Company","symbol":"N/A","percent":"8.02","return":"N/A"},{"company":"Fidelity Series International Growth","symbol":"N/A","percent":"7.77","return":"N/A"},{"company":"Fidelity Series International Value","symbol":"N/A","percent":"7.66","return":"N/A"},{"company":"Fidelity Series 100 Index","symbol":"N/A","percent":"7.13","return":"N/A"},{"company":"Fidelity Series High Income","symbol":"N/A","percent":"6.96","return":"N/A"},{"company":"Fidelity Disciplined Equity","symbol":"N/A","percent":"5.34","return":"N/A"}]