[{"company":"Apple Inc.","symbol":"AAPL","percent":"4.63","return":"63.47"},{"company":"Exxon Mobil Corporation Common","symbol":"XOM","percent":"2.83","return":"10.21"},{"company":"Chevron Corporation Common Stoc","symbol":"CVX","percent":"2.12","return":"12.65"},{"company":"Microsoft Corporation","symbol":"MSFT","percent":"2.09","return":"15.91"},{"company":"General Electric Company Common","symbol":"GE","percent":"2.06","return":"30.21"},{"company":"AT&T Inc.","symbol":"T","percent":"1.98","return":"29.20"},{"company":"Johnson & Johnson Common Stock","symbol":"JNJ","percent":"1.75","return":"8.14"},{"company":"Pfizer, Inc. Common Stock","symbol":"PFE","percent":"1.72","return":"18.74"},{"company":"Google Inc.","symbol":"GOOG","percent":"1.72","return":"17.94"},{"company":"Wells Fargo & Company Common St","symbol":"WFC","percent":"1.72","return":"28.30"}]