[{"company":"Kogas","symbol":"036460.KS","percent":"2.28","return":"Hopewell Holdings Ltd."},{"company":"00054.HK","symbol":"2.03","percent":"Hysan Development Co., Ltd.","return":"HYSNF.HK"},{"company":"2.02","symbol":"Cheung Kong Holdings, Ltd.","percent":"00001.HK","return":"1.95"},{"company":"FirstRes","symbol":"EB5.SI","percent":"1.91","return":"Wharf holdings"},{"company":"00004.HK","symbol":"1.88","percent":"Wheelock and Co., Ltd.","return":"00020.HK"},{"company":"1.84","symbol":"Swire Pacific Ltd. Class A","percent":"SWRAF.HK","return":"1.83"},{"company":"KorZinc","symbol":"010130.KS","percent":"1.81","return":"Champion Real Estate Investment Trust"},{"company":"CMPNF.HK","symbol":"1.79","percent":null,"return":null}]