[{"company":"Aberdeen Equity Long-Short Inst","symbol":"N/A","percent":"11.76","return":"N/A"},{"company":"iShares S&P Global Healthcare","symbol":"N/A","percent":"11.15","return":"N/A"},{"company":"Aberdeen Natural Resources I","symbol":"N/A","percent":"10.94","return":"N/A"},{"company":"Aberdeen Global Financial Services Inst","symbol":"N/A","percent":"10.77","return":"N/A"},{"company":"Aberdeen Emerging Markets Instl Fd Instl","symbol":"N/A","percent":"9.60","return":"N/A"},{"company":"iShares S&P Global Infrastructure Index","symbol":"N/A","percent":"8.52","return":"N/A"},{"company":"iShares S&P Global Technology","symbol":"N/A","percent":"7.95","return":"N/A"},{"company":"SPDR Dow Jones Intl Real Estate","symbol":"N/A","percent":"5.93","return":"N/A"},{"company":"Credit Suisse Commodity Return Strat Com","symbol":"N/A","percent":"5.75","return":"N/A"},{"company":"Aberdeen International Eq Instl Fd Instl","symbol":"N/A","percent":"4.99","return":"N/A"}]