[{"company":"The Ultimate Software Group, In","symbol":"ULTI","percent":"1.55","return":"53.49"},{"company":"Align Technology, Inc.","symbol":"ALGN","percent":"1.54","return":"48.28"},{"company":"Russell 2000 Mini Index Ftrs Sep12 Icus","symbol":"N/A","percent":"1.46","return":"6.40"},{"company":"Lancaster Colony Corporation","symbol":"LANC","percent":"1.42","return":"-5.00"},{"company":"Boston Beer Company, Inc. (The)","symbol":"SAM","percent":"1.39","return":"17.55"},{"company":"Jazz Pharmaceuticals plc","symbol":"JAZZ","percent":"1.36","return":"39.76"},{"company":"Papa John'S International, Inc.","symbol":"PZZA","percent":"1.31","return":"0.72"},{"company":"Zumiez Inc.","symbol":"ZUMZ","percent":"1.30","return":"32.51"},{"company":"Omega Healthcare Investors, Inc","symbol":"OHI","percent":"1.28","return":"-11.08"},{"company":"Blackbaud, Inc.","symbol":"BLKB","percent":"1.24","return":"N/A"}]