[{"company":"Dominion Resources Black Warrio","symbol":"DOM","percent":"1.55","return":"27.98"},{"company":"Domino's Pizza UK & IRL PLC","symbol":"N/A","percent":"1.54","return":"N/A"},{"company":"Benesse Holdings Inc","symbol":"N/A","percent":"1.48","return":"N/A"},{"company":"Kodiak Oil & Gas Corp Common St","symbol":"KOG","percent":"1.37","return":"N/A"},{"company":"Sa Sa International Holdings Ltd.","symbol":"178","percent":"1.29","return":"N/A"},{"company":"CH Energy Group, Inc. Common St","symbol":"CHG","percent":"1.24","return":"N/A"},{"company":"ASICS Corp","symbol":"7936","percent":"1.22","return":"N/A"},{"company":"CATHAY PACIFIC AIRWA","symbol":"CPCAF","percent":"1.22","return":"N/A"},{"company":"Square Enix Hldgs Co Ltd","symbol":"N/A","percent":"1.21","return":"N/A"},{"company":"TEAM NATION HOLDINGS","symbol":"TEMN","percent":"1.21","return":"N/A"}]