[{"company":"US Treasury Note","symbol":"N/A","percent":"4.56","return":"19.58"},{"company":"US Treasury Note 0.125%","symbol":"N/A","percent":"3.39","return":"2.09"},{"company":"Simon Property Group, Inc. Comm","symbol":"SPG","percent":"3.28","return":"5.80"},{"company":"US Treasury Bond 2.5%","symbol":"N/A","percent":"2.17","return":"15.51"},{"company":"Equity Residential Common Share","symbol":"EQR","percent":"1.86","return":"5.92"},{"company":"FNMA 3.5%","symbol":"N/A","percent":"1.59","return":"11.54"},{"company":"Public Storage Common Stock","symbol":"PSA","percent":"1.39","return":"N/A"},{"company":"Ventas, Inc. Common Stock","symbol":"VTR","percent":"1.30","return":"N/A"},{"company":"AvalonBay Communities, Inc. Com","symbol":"AVB","percent":"1.24","return":"N/A"},{"company":"Boston Properties, Inc. Common","symbol":"BXP","percent":"1.23","return":"N/A"}]