[{"company":"JHVIT Bond NAV","symbol":"N/A","percent":"34.21","return":"N/A"},{"company":"JHVIT New Income Trust Ser NAV","symbol":"N/A","percent":"15.98","return":"N/A"},{"company":"JHVIT Total Return Trust Ser NAV","symbol":"N/A","percent":"15.09","return":"N/A"},{"company":"JHVIT Core Bond Trust Ser NAV","symbol":"N/A","percent":"9.58","return":"N/A"},{"company":"JHVIT Strategic Equity Allocation NAV","symbol":"N/A","percent":"8.09","return":"N/A"},{"company":"JHVIT Global Bond Trust Ser NAV","symbol":"N/A","percent":"3.36","return":"N/A"},{"company":"JHVIT Blue Chip Growth Trust Ser NAV","symbol":"N/A","percent":"2.42","return":"N/A"},{"company":"JHVIT Equity-Income Trust Ser NAV","symbol":"N/A","percent":"2.37","return":"N/A"},{"company":"JHVIT Short Term Gov Inc Tr Ser NAV","symbol":"N/A","percent":"1.59","return":"N/A"},{"company":"JHVIT Fundamental Value Trust Ser NAV","symbol":"N/A","percent":"1.51","return":"N/A"}]