[{"company":"Catamaran Corp","symbol":"CTRX.TO","percent":"3.47","return":"75.50"},{"company":"Alliance Data Systems Corporati","symbol":"ADS","percent":"2.70","return":"36.28"},{"company":"PetSmart, Inc","symbol":"PETM","percent":"2.39","return":"32.59"},{"company":"Whole Foods Market, Inc.","symbol":"WFM","percent":"2.37","return":"40.92"},{"company":"Alexion Pharmaceuticals, Inc.","symbol":"ALXN","percent":"2.27","return":"62.24"},{"company":"Kansas City Southern Common Sto","symbol":"KSU","percent":"2.05","return":"12.23"},{"company":"Apple Inc.","symbol":"AAPL","percent":"1.91","return":"63.47"},{"company":"Mead Johnson Nutrition Company","symbol":"MJN","percent":"1.81","return":"7.46"},{"company":"SBA Communications Corporation","symbol":"SBAC","percent":"1.75","return":"47.04"},{"company":"Perrigo Company","symbol":"PRGO","percent":"1.66","return":"20.78"}]