[{"company":"JPMorgan Core Bond R6","symbol":"N/A","percent":"28.66","return":"N/A"},{"company":"JPMorgan High Yield R6","symbol":"N/A","percent":"11.21","return":"N/A"},{"company":"JPMorgan Disciplined Equity R6","symbol":"N/A","percent":"9.29","return":"N/A"},{"company":"JPMorgan Inflation Managed Bond R6","symbol":"N/A","percent":"6.46","return":"N/A"},{"company":"JPMorgan Emerging Markets Debt R6","symbol":"N/A","percent":"5.01","return":"N/A"},{"company":"JPMorgan Real Return Instl","symbol":"N/A","percent":"3.29","return":"N/A"},{"company":"JPMorgan Intl Opp R6","symbol":"N/A","percent":"2.75","return":"N/A"},{"company":"JPMorgan Growth Advantage R5","symbol":"N/A","percent":"2.67","return":"N/A"},{"company":"JPMorgan Value Advantage Instl","symbol":"N/A","percent":"2.57","return":"N/A"},{"company":"JPMorgan International Equity R6","symbol":"N/A","percent":"2.50","return":"N/A"}]