[{"company":"Connecticut St Health & Edl Fa Ed F 4.7%","symbol":"N/A","percent":"2.55","return":"N/A"},{"company":"Connecticut St Dev Auth 4.375%","symbol":"N/A","percent":"2.54","return":"N/A"},{"company":"New Haven Conn Go Ref Bd 5%","symbol":"N/A","percent":"2.36","return":"N/A"},{"company":"Connecticut St Go Bds 5%","symbol":"N/A","percent":"2.12","return":"N/A"},{"company":"Connecticut St Spl Tax Obl R Spl Ta 4.5%","symbol":"N/A","percent":"2.12","return":"N/A"},{"company":"Conn St Gen Rev General R 5%","symbol":"N/A","percent":"2.11","return":"N/A"},{"company":"Conn St Hsg Fin Auth 4.55%","symbol":"N/A","percent":"2.05","return":"N/A"},{"company":"Connecticut St Spl Tax Obl R Special 5%","symbol":"N/A","percent":"1.97","return":"N/A"},{"company":"Connecticut St Health & Edl Fa Rev 4.75%","symbol":"N/A","percent":"1.77","return":"N/A"}]