[{"company":"Samsung Electronics Co Ltd","symbol":"SSNLF.KS","percent":"5.27","return":"44.91"},{"company":"Industrial And Commercial Bank Of China Ltd.","symbol":"01398","percent":"2.06","return":"3.46"},{"company":"KiaMtr","symbol":"000270.KS","percent":"1.84","return":"-12.58"},{"company":"Companhia de Bebidas das Americas Ambev ADR","symbol":"ABV.SA","percent":"1.71","return":"9.06"},{"company":"CNOOC, Ltd.","symbol":"00883","percent":"1.68","return":"-2.76"},{"company":"HyundaiMtr","symbol":"005380.KS","percent":"1.56","return":"N/A"},{"company":"Petroleo Brasileiro SA Petrobras ADR","symbol":"PBR.A.SA","percent":"1.46","return":"N/A"},{"company":"LUKOIL CO SPONS ADR","symbol":"LUKOY","percent":"1.41","return":"N/A"},{"company":"China Mobile Ltd.","symbol":"00941","percent":"1.37","return":"N/A"},{"company":"BANK OF CHINA BEIJIN","symbol":"BACHF","percent":"1.36","return":"N/A"}]