[{"company":"United Kingdom (Government Of) 4.25%","symbol":"N/A","percent":"10.66","return":"N/A"},{"company":"Italy(Rep Of) 5%","symbol":"N/A","percent":"9.70","return":"N/A"},{"company":"Mex Bonos Desarr Fix Rt Bonds 05/29 8.5","symbol":"N/A","percent":"9.08","return":"N/A"},{"company":"New Sth Wales Tsy 6%","symbol":"N/A","percent":"9.03","return":"N/A"},{"company":"New Zealand Government Sr Unsecured 04/23 5.5","symbol":"N/A","percent":"4.91","return":"N/A"},{"company":"Poland(Rep Of) 5.75%","symbol":"N/A","percent":"4.69","return":"N/A"},{"company":"Malaysia 3.741%","symbol":"N/A","percent":"3.79","return":"N/A"},{"company":"Queensland Treasury Corp Local Govt G 02/20 6.25","symbol":"N/A","percent":"3.77","return":"N/A"},{"company":"Nota Do Tesouro Nacional Notes 01/21 10.","symbol":"N/A","percent":"3.70","return":"N/A"},{"company":"Hungary(Rep Of) 5.5%","symbol":"N/A","percent":"3.58","return":"N/A"}]