[{"company":"ProAssurance Corporation Common","symbol":"PRA","percent":"1.62","return":"14.87"},{"company":"Aaron's, Inc. Common Stock","symbol":"AAN","percent":"1.32","return":"3.20"},{"company":"Cleco Corporation Common Stock","symbol":"CNL","percent":"1.29","return":"12.29"},{"company":"Landstar System, Inc.","symbol":"LSTR","percent":"1.23","return":"-1.67"},{"company":"Nordson Corporation","symbol":"NDSN","percent":"0.97","return":"42.01"},{"company":"Beacon Roofing Supply, Inc.","symbol":"BECN","percent":"0.92","return":"39.20"},{"company":"Kirby Corporation Common Stock","symbol":"KEX","percent":"0.85","return":"-15.87"},{"company":"Genesee & Wyoming Inc. Class A","symbol":"GWR","percent":"0.82","return":"11.84"},{"company":"SVB Financial Group","symbol":"SIVB","percent":"0.80","return":"27.28"},{"company":"Alterra Capital Holdings Limite","symbol":"ALTE","percent":"0.79","return":"4.10"}]