[{"company":"Pennsylvania St Go Ref Bd 5%","symbol":"N/A","percent":"2.98","return":"N/A"},{"company":"Pennsylvania St Go Bds Fi 5%","symbol":"N/A","percent":"2.23","return":"N/A"},{"company":"State Pub Sch Bldg Auth 5.25%","symbol":"N/A","percent":"1.64","return":"N/A"},{"company":"Allentown Pa Sch Dist 5%","symbol":"N/A","percent":"1.60","return":"N/A"},{"company":"California St Various P 5.5%","symbol":"N/A","percent":"1.54","return":"N/A"},{"company":"Pennsylvania St Higher Edl Fac Rev Bd 5%","symbol":"N/A","percent":"1.50","return":"N/A"},{"company":"Foothill / Eastern Transn Corr Toll Rd","symbol":"N/A","percent":"1.48","return":"N/A"},{"company":"Pennsylvania St Higher Edl Fac Rev 5.25%","symbol":"N/A","percent":"1.48","return":"N/A"},{"company":"Pennsylvania St Tpk Commn Regi Rev 5.25%","symbol":"N/A","percent":"1.48","return":"N/A"}]