[{"company":"Simon Property Group, Inc. Comm","symbol":"SPG","percent":"14.29","return":"19.58"},{"company":"Equity Residential Common Share","symbol":"EQR","percent":"9.15","return":"2.09"},{"company":"Vornado Realty Trust Common Sto","symbol":"VNO","percent":"6.32","return":"7.16"},{"company":"Host Hotels & Resorts, Inc. Com","symbol":"HST","percent":"5.35","return":"8.12"},{"company":"HCP, Inc. Common Stock","symbol":"HCP","percent":"5.25","return":"10.67"},{"company":"Regency Centers Corporation Com","symbol":"REG","percent":"4.59","return":"32.45"},{"company":"Boston Properties, Inc. Common","symbol":"BXP","percent":"4.23","return":"11.54"},{"company":"General Growth Properties, Inc.","symbol":"GGP","percent":"4.06","return":"32.75"},{"company":"Public Storage Common Stock","symbol":"PSA","percent":"3.78","return":"5.80"},{"company":"AvalonBay Communities, Inc. Com","symbol":"AVB","percent":"3.13","return":"5.92"}]