[{"company":"Tennessee Engy Acquisition C Jr R 5.625%","symbol":"N/A","percent":"1.05","return":"N/A"},{"company":"Allegheny Cnty Pa Hosp Dev Aut Re 5.375%","symbol":"N/A","percent":"0.87","return":"N/A"},{"company":"Tulsa Okla Mun Arpt Tr Rev Rev Bds 6.25%","symbol":"N/A","percent":"0.68","return":"N/A"},{"company":"Tobacco Settlement Fing Corp V Asset 5%","symbol":"N/A","percent":"0.66","return":"N/A"},{"company":"Pennsylvania Econ Dev Fing Rev Bds 6%","symbol":"N/A","percent":"0.63","return":"N/A"},{"company":"Harbor Point Infrasct Im Spl Obl 7.875%","symbol":"N/A","percent":"0.61","return":"N/A"},{"company":"Tolomato Cmnty Dev Dist 5.4%","symbol":"N/A","percent":"0.57","return":"N/A"},{"company":"River Rock Entmt Auth 8%","symbol":"N/A","percent":"0.55","return":"N/A"},{"company":"Central Plains Engy Proj Neb Gas Proj 5%","symbol":"N/A","percent":"0.54","return":"N/A"},{"company":"Wisconsin Pub Fin Auth 8.625%","symbol":"N/A","percent":"0.53","return":"N/A"}]