[{"company":"Pfizer, Inc. Common Stock","symbol":"PFE","percent":"3.07","return":"12.92"},{"company":"Exxon Mobil Corporation Common","symbol":"XOM","percent":"2.90","return":"4.68"},{"company":"General Electric Company Common","symbol":"GE","percent":"2.61","return":"16.42"},{"company":"Wells Fargo & Company Common St","symbol":"WFC","percent":"2.60","return":"25.04"},{"company":"Johnson & Johnson Common Stock","symbol":"JNJ","percent":"2.47","return":"5.29"},{"company":"JP Morgan Chase & Co. Common St","symbol":"JPM","percent":"2.08","return":"13.86"},{"company":"Occidental Petroleum Corporatio","symbol":"OXY","percent":"2.03","return":"-10.15"},{"company":"Citigroup, Inc. Common Stock","symbol":"C","percent":"1.80","return":"13.00"},{"company":"Capital One Financial Corporati","symbol":"COF","percent":"1.75","return":"33.93"},{"company":"Merck & Company, Inc. Common St","symbol":"MRK","percent":"1.70","return":"16.95"}]