[{"company":"PIMCO Emerging Markets Currency Instl","symbol":"N/A","percent":"13.10","return":"N/A"},{"company":"PIMCO High Yield Instl","symbol":"N/A","percent":"11.69","return":"N/A"},{"company":"PIMCO Emerging Local Bond Instl","symbol":"N/A","percent":"11.49","return":"N/A"},{"company":"PIMCO EM Fdmtl IndexPLUS TR ST Instl","symbol":"N/A","percent":"9.32","return":"N/A"},{"company":"PIMCO CommoditiesPLUS Strategy Instl","symbol":"N/A","percent":"8.45","return":"N/A"},{"company":"PIMCO Emerging Markets Bond Instl","symbol":"N/A","percent":"7.61","return":"N/A"},{"company":"PIMCO Income Instl","symbol":"N/A","percent":"7.09","return":"N/A"},{"company":"PIMCO StocksPLUS TR Short Strat Instl","symbol":"N/A","percent":"6.97","return":"N/A"},{"company":"PIMCO Intl Fdmtl IdxPLUS TR Strat Instl","symbol":"N/A","percent":"6.64","return":"N/A"},{"company":"PIMCO Floating Income Instl","symbol":"N/A","percent":"6.35","return":"N/A"}]