[{"company":"Crown Castle International Corp","symbol":"CCI","percent":"2.96","return":"42.37"},{"company":"VeriSign, Inc.","symbol":"VRSN","percent":"2.36","return":"36.60"},{"company":"Ross Stores, Inc.","symbol":"ROST","percent":"2.22","return":"40.06"},{"company":"DaVita Inc. Common Stock","symbol":"DVA","percent":"1.82","return":"36.45"},{"company":"AMETEK, Inc.","symbol":"AME","percent":"1.81","return":"24.31"},{"company":"Roper Industries, Inc. Common S","symbol":"ROP","percent":"1.78","return":"26.21"},{"company":"Annaly Capital Management Inc C","symbol":"NLY","percent":"1.71","return":"15.10"},{"company":"PVH Corp. Common Stock","symbol":"PVH","percent":"1.70","return":"32.02"},{"company":"Dollar Tree, Inc.","symbol":"DLTR","percent":"1.68","return":"16.23"},{"company":"Henry Schein, Inc.","symbol":"HSIC","percent":"1.67","return":"22.93"}]