[{"company":"Regeneron Pharmaceuticals, Inc.","symbol":"REGN","percent":"1.01","return":"178.59"},{"company":"Vertex Pharmaceuticals Incorpor","symbol":"VRTX","percent":"0.98","return":"69.95"},{"company":"Equinix, Inc.","symbol":"EQIX","percent":"0.83","return":"100.42"},{"company":"Kansas City Southern Common Sto","symbol":"KSU","percent":"0.74","return":"12.23"},{"company":"HollyFrontier Corporation Commo","symbol":"HFC","percent":"0.73","return":"87.48"},{"company":"AMETEK, Inc.","symbol":"AME","percent":"0.72","return":"24.31"},{"company":"Macerich Company (The) Common S","symbol":"MAC","percent":"0.69","return":"15.36"},{"company":"PetSmart, Inc","symbol":"PETM","percent":"0.67","return":"32.59"},{"company":"Church & Dwight Company, Inc. C","symbol":"CHD","percent":"0.67","return":"20.56"},{"company":"SL Green Realty Corporation Com","symbol":"SLG","percent":"0.63","return":"19.46"}]