[{"company":"US Treasury Note 2.25%","symbol":"N/A","percent":"8.07","return":"US Treasury Note 0.5%"},{"company":"N/A","symbol":"8.04","percent":"US Treasury Note 1.875%","return":"N/A"},{"company":"7.98","symbol":"FNMA 0.75%","percent":"N/A","return":"5.98"},{"company":"FHLBA 0.5%","symbol":"N/A","percent":"5.94","return":"FNMA 0.5%"},{"company":"N/A","symbol":"5.94","percent":"US Treasury Note 0.25%","return":"N/A"},{"company":"5.33","symbol":"FHLMC 0.5%","percent":"N/A","return":"4.46"},{"company":"US Treasury Note 2.125%","symbol":"N/A","percent":"3.14","return":null}]