[{"company":"Fidelity Instl MM Fds Prime MMkt I","symbol":"N/A","percent":"3.10","return":"64.72"},{"company":"Global Cash Access Holdings, In","symbol":"GCA","percent":"2.13","return":"80.22"},{"company":"GP Strategies Corporation Commo","symbol":"GPX","percent":"1.92","return":"44.21"},{"company":"BioScrip, Inc.","symbol":"BIOS","percent":"1.84","return":"69.60"},{"company":"John B. Sanfilippo & Son, Inc.","symbol":"JBSS","percent":"1.77","return":"74.27"},{"company":"Innodata Inc.","symbol":"INOD","percent":"1.76","return":"4.82"},{"company":"Aceto Corporation","symbol":"ACET","percent":"1.50","return":"39.78"},{"company":"KMG Chemicals, Inc. Common Stoc","symbol":"KMG","percent":"1.42","return":"6.83"},{"company":"PRGX Global, Inc.","symbol":"PRGX","percent":"1.41","return":"43.70"},{"company":"Vaalco Energy Inc Common Stock","symbol":"EGY","percent":"1.40","return":"42.38"}]