[{"company":"Urban Outfitters, Inc.","symbol":"URBN","percent":"1.08","return":"LKQ Corporation"},{"company":"LKQ","symbol":"1.06","percent":"Senior Housing Properties Trust","return":"SNH"},{"company":"1.03","symbol":"Biomed Realty Trust Common Stoc","percent":"BMR","return":"1.01"},{"company":"tw telecom inc.","symbol":"TWTC","percent":"0.96","return":"Scripps Networks Interactive, I"},{"company":"SNI","symbol":"0.94","percent":"Dresser-Rand Group Inc. Common","return":"DRC"},{"company":"0.92","symbol":"ResMed Inc. Common Stock","percent":"RMD","return":"0.92"},{"company":"Level 3 Communications, Inc. Co","symbol":"LVLT","percent":"0.88","return":"National Retail Properties Comm"},{"company":"NNN","symbol":"0.87","percent":null,"return":null}]