[{"company":"First American Corporation (New","symbol":"FAF","percent":"3.03","return":"72.61"},{"company":"ITT Corporation Common Stock Ne","symbol":"ITT","percent":"2.87","return":"4.77"},{"company":"Collective Brands, Inc. Common","symbol":"PSS","percent":"2.83","return":"51.22"},{"company":"Exelis Inc. Common Stock New","symbol":"XLS","percent":"2.82","return":"19.56"},{"company":"Community Health Systems, Inc.","symbol":"CYH","percent":"2.59","return":"70.54"},{"company":"JetBlue Airways Corporation","symbol":"JBLU","percent":"2.19","return":"-6.44"},{"company":"Ingram Micro Inc. Common Stock","symbol":"IM","percent":"2.13","return":"-16.27"},{"company":"Protective Life Corporation Com","symbol":"PL","percent":"2.06","return":"18.31"},{"company":"URS Corporation Common Stock","symbol":"URS","percent":"2.05","return":"3.39"},{"company":"Huntington Ingalls Industries,","symbol":"HII","percent":"1.93","return":"34.37"}]