[{"company":"Guggenheim US Long Short Momentum A","symbol":"N/A","percent":"19.09","return":"N/A"},{"company":"Sg Large Cap Concentrated Growth Class A","symbol":"N/A","percent":"9.40","return":"N/A"},{"company":"Rydex|SGI Large Cap Value A","symbol":"N/A","percent":"9.37","return":"N/A"},{"company":"Guggenheim US Intermediate Bond A","symbol":"N/A","percent":"9.05","return":"N/A"},{"company":"iShares Barclays Aggregate Bond","symbol":"N/A","percent":"7.51","return":"N/A"},{"company":"Guggenheim MSCI EAFE Equal Weight A","symbol":"N/A","percent":"5.45","return":"N/A"},{"company":"Guggenheim Multi-Hedge Strategies A","symbol":"N/A","percent":"4.44","return":"N/A"},{"company":"Guggenheim Long Short Int Rate Strat A","symbol":"N/A","percent":"3.51","return":"N/A"},{"company":"Rydex|SGI Mid Cap Value A","symbol":"N/A","percent":"2.45","return":"N/A"},{"company":"Rydex|SGI Mid Cap Growth A","symbol":"N/A","percent":"2.44","return":"N/A"}]