[{"company":"ROYAL DUTCH SHELL-B","symbol":"RDSB.L","percent":"2.71","return":"2.30"},{"company":"GlaxoSmithKline PLC","symbol":"GLAXF.L","percent":"2.59","return":"0.20"},{"company":"Volkswagen AG","symbol":"VW-V.DE","percent":"2.10","return":"N/A"},{"company":"Santander Futuro 2025 2 PP","symbol":"SAN.BC","percent":"2.05","return":"N/A"},{"company":"TOTAL","symbol":"FP.PA","percent":"1.88","return":"N/A"},{"company":"iShares MSCI EAFE Index","symbol":"N/A","percent":"1.85","return":"N/A"},{"company":"METRO","symbol":"MEO.DE","percent":"1.81","return":"N/A"},{"company":"Hitachi, Ltd.","symbol":"6501","percent":"1.81","return":"N/A"},{"company":"RIO TINTO","symbol":"RIO.L","percent":"1.79","return":"N/A"},{"company":"Transocean Ltd (Switzerland) Co","symbol":"RIG","percent":"1.74","return":"N/A"}]