[{"company":"California Hsg Fin Agy Rev Rev Bd 5.375%","symbol":"N/A","percent":"7.83","return":"N/A"},{"company":"Lakeside Calif Un Sch Dist 5%","symbol":"N/A","percent":"6.16","return":"N/A"},{"company":"California Edl Facs Auth 5%","symbol":"N/A","percent":"5.43","return":"N/A"},{"company":"Washington Twp Calif Health Ca Rev 5.25%","symbol":"N/A","percent":"5.13","return":"N/A"},{"company":"Foothill / Eastern Transn Corr Tol 5.75%","symbol":"N/A","percent":"4.85","return":"N/A"},{"company":"California St Go Bds 5.75%","symbol":"N/A","percent":"4.01","return":"N/A"},{"company":"Palmdale Calif Civic Auth 6%","symbol":"N/A","percent":"3.93","return":"N/A"},{"company":"Los Angeles Calif Mun Impt Cor Lse Re 5%","symbol":"N/A","percent":"3.85","return":"N/A"},{"company":"California St Go Bds 5%","symbol":"N/A","percent":"3.65","return":"N/A"},{"company":"California Health Facs Fing Au Rev 5.75%","symbol":"N/A","percent":"3.64","return":"N/A"}]