[{"company":"Ssc Goverment Mm Gvxx","symbol":"N/A","percent":"7.69","return":"N/A"},{"company":"Fannie Mae Single Family TBA 2.5% 2027-09-01","symbol":"N/A","percent":"5.22","return":"N/A"},{"company":"Fannie Mae Single Family TBA 2.5% 2027-10-01","symbol":"N/A","percent":"2.08","return":"N/A"},{"company":"FNMA CMO","symbol":"N/A","percent":"1.99","return":"N/A"},{"company":"FHLMC FRN","symbol":"N/A","percent":"1.73","return":"N/A"},{"company":"FNMA 6.255%","symbol":"N/A","percent":"1.58","return":"N/A"}]