[{"company":"First Solar, Inc.","symbol":"FSLR","percent":"6.60","return":"GCL-Poly Energy Holdings Limited"},{"company":"03800","symbol":"6.21","percent":"Power-One, Inc.","return":"PWER"},{"company":"5.46","symbol":"Meyer Burger Technology AG","percent":"MBTN","return":"5.35"},{"company":"SMA SOLAR TECH","symbol":"S92.DE","percent":"5.32","return":"Trina Solar Limited Sponsored A"},{"company":"TSL","symbol":"5.24","percent":"Renewable Energy Corporation ASA","return":"REC"},{"company":"5.20","symbol":"GT Advanced Technologies, Inc.","percent":"GTAT","return":"5.13"},{"company":"SOLARWORLD","symbol":"SWV.DE","percent":"4.67","return":"MEMC Electronic Materials, Inc."},{"company":"WFR","symbol":"4.61","percent":null,"return":null}]