[{"company":"US Treasury Note 2.625%","symbol":"N/A","percent":"11.67","return":"US Treasury Note 3.625%"},{"company":"N/A","symbol":"11.62","percent":"US Treasury Bond 8.125%","return":"N/A"},{"company":"11.49","symbol":"US Treasury Bond 7.625%","percent":"N/A","return":"9.56"},{"company":"US Treasury Bond 8.75%","symbol":"N/A","percent":"9.47","return":"US Treasury Note 3.375%"},{"company":"N/A","symbol":"7.77","percent":"US Treasury Bond 6.25%","return":"N/A"},{"company":"6.43","symbol":"US Treasury Note 2%","percent":"N/A","return":"6.01"},{"company":"US Treasury Bond 6%","symbol":"N/A","percent":"5.91","return":"US Treasury Bond 6.375%"},{"company":"N/A","symbol":"5.02","percent":null,"return":null}]