[{"company":"SPDR Gold Shares","symbol":"N/A","percent":"6.49","return":"10.21"},{"company":"Exxon Mobil Corporation Common","symbol":"XOM","percent":"3.93","return":"6.69"},{"company":"PowerShares DB Agriculture","symbol":"N/A","percent":"3.56","return":"30.94"},{"company":"POTASH CORP OF SASK INC","symbol":"POT.TO","percent":"3.33","return":"N/A"},{"company":"US Treasury Note 2%","symbol":"N/A","percent":"3.33","return":"N/A"},{"company":"US Treasury Bond 1.75%","symbol":"N/A","percent":"3.22","return":"N/A"},{"company":"US Treasury Note 2.125%","symbol":"N/A","percent":"3.22","return":"N/A"},{"company":"US Treasury Bond","symbol":"N/A","percent":"2.93","return":"N/A"},{"company":"Syngenta AG Common Stock","symbol":"SYT","percent":"2.85","return":"N/A"},{"company":"US Treasury Bond 2.375%","symbol":"N/A","percent":"2.73","return":"N/A"}]