[{"company":"Lewisville Tex Combination Con Ref 5.8%","symbol":"N/A","percent":"3.75","return":"63.47"},{"company":"Apple Inc.","symbol":"AAPL","percent":"2.00","return":"N/A"},{"company":"Orlando Fla Tourist Dev Tax Re Sr 5.125%","symbol":"N/A","percent":"1.97","return":"N/A"},{"company":"Metropolitan Transn Auth 5%","symbol":"N/A","percent":"1.96","return":"N/A"},{"company":"Michigan St Hosp Fin Auth 5%","symbol":"N/A","percent":"1.91","return":"N/A"},{"company":"Rockport Ind Pollution Ctl Rev Po 4.625%","symbol":"N/A","percent":"1.91","return":"N/A"},{"company":"Oneida Cnty N Y Indl Dev Agy C Civic Fac","symbol":"N/A","percent":"1.87","return":"N/A"},{"company":"Mashantucket Western Pequot Tr Sub 5.75%","symbol":"N/A","percent":"1.48","return":"N/A"},{"company":"Illinois Fin Auth 6%","symbol":"N/A","percent":"1.46","return":"N/A"},{"company":"Piedmont Mun Pwr Agy S C Elec Elec 5.75%","symbol":"N/A","percent":"1.45","return":"N/A"}]