[{"company":"ConocoPhillips Common Stock","symbol":"COP","percent":"7.53","return":"6.63"},{"company":"General Electric Company Common","symbol":"GE","percent":"6.61","return":"30.21"},{"company":"Molson Coors Brewing Company Cl","symbol":"TAP","percent":"5.68","return":"0.55"},{"company":"American Express Company Common","symbol":"AXP","percent":"5.54","return":"23.62"},{"company":"Goldman Sachs Group, Inc. (The)","symbol":"GS","percent":"4.92","return":"30.63"},{"company":"Diebold, Incorporated Common St","symbol":"DBD","percent":"4.62","return":"13.45"},{"company":"AT&T Inc.","symbol":"T","percent":"4.55","return":"29.20"},{"company":"ProShares UltraPro Short S&P500","symbol":"N/A","percent":"4.05","return":"9.97"},{"company":"Harley-Davidson, Inc. Common St","symbol":"HOG","percent":"3.90","return":"16.31"},{"company":"3M Company Common Stock","symbol":"MMM","percent":"3.83","return":"N/A"}]