[{"company":"BHP Billiton Ltd","symbol":"BHPLF.AX","percent":"2.00","return":"0.67"},{"company":"NESTLE SA CHAM ET VE","symbol":"NSRGF","percent":"1.78","return":"12.87"},{"company":"CWLTH BANK FPO","symbol":"CBA.AX","percent":"1.76","return":"27.41"},{"company":"Msci Eafe Mini Index Futures Sep12 Xnli","symbol":"N/A","percent":"1.66","return":"2.55"},{"company":"Westpac Banking Corp","symbol":"WBC.L","percent":"1.37","return":"22.71"},{"company":"HSBC Holdings PLC","symbol":"HBCYF.L","percent":"1.32","return":"10.44"},{"company":"Vodafone Group PLC","symbol":"VODPF.AX","percent":"1.25","return":"-0.99"},{"company":"AUSTRALIA & N Z BKG","symbol":"ANEWF","percent":"1.22","return":"N/A"},{"company":"Novartis AG","symbol":"NVSEF.L","percent":"1.18","return":"N/A"},{"company":"BP PLC","symbol":"BPAQF","percent":"1.11","return":"N/A"}]