[{"company":"Invesco Balanced-Risk Allc Instl","symbol":"N/A","percent":"15.83","return":"N/A"},{"company":"Invesco Diversified Dividend Instl","symbol":"N/A","percent":"9.23","return":"N/A"},{"company":"Invesco Van Kampen Capital Growth I","symbol":"N/A","percent":"8.64","return":"N/A"},{"company":"Invesco Intl Core Equity Institutional","symbol":"N/A","percent":"8.62","return":"N/A"},{"company":"Invesco Van Kampen Intl Gr I","symbol":"N/A","percent":"8.13","return":"N/A"},{"company":"Invesco Developing Markets Instl","symbol":"N/A","percent":"7.40","return":"N/A"},{"company":"PowerShares 1-30 Laddered Treasury","symbol":"N/A","percent":"6.99","return":"N/A"},{"company":"Invesco Charter I","symbol":"N/A","percent":"6.08","return":"N/A"},{"company":"Invesco Balanced Risk Cmdty Strat Instl","symbol":"N/A","percent":"5.95","return":"N/A"},{"company":"Invesco Van Kampen Comstock Instl","symbol":"N/A","percent":"5.60","return":"N/A"}]