[{"company":"Wells Fargo & Company Common St","symbol":"WFC","percent":"3.43","return":"28.30"},{"company":"Pfizer, Inc. Common Stock","symbol":"PFE","percent":"2.34","return":"18.74"},{"company":"Comcast Corporation","symbol":"CMCSK","percent":"2.12","return":"48.25"},{"company":"Merck & Company, Inc. Common St","symbol":"MRK","percent":"1.91","return":"23.28"},{"company":"UnitedHealth Group Incorporated","symbol":"UNH","percent":"1.85","return":"12.56"},{"company":"Arrow Electronics, Inc. Common","symbol":"ARW","percent":"1.80","return":"-8.85"},{"company":"Cisco Systems, Inc.","symbol":"CSCO","percent":"1.63","return":"6.53"},{"company":"Exxon Mobil Corporation Common","symbol":"XOM","percent":"1.59","return":"10.21"},{"company":"JP Morgan Chase & Co. Common St","symbol":"JPM","percent":"1.53","return":"25.77"},{"company":"Ace Limited Common Stock","symbol":"ACE","percent":"1.52","return":"12.46"}]