[{"company":"Crown Castle International Corp","symbol":"CCI","percent":"24.42","return":"42.37"},{"company":"Sprint  Nextel Corporation Comm","symbol":"S","percent":"13.14","return":"121.37"},{"company":"SBA Communications Corporation","symbol":"SBAC","percent":"10.43","return":"47.04"},{"company":"Telephone and Data Systems, Inc","symbol":"TDS","percent":"4.37","return":"8.14"},{"company":"NII Holdings, Inc.","symbol":"NIHD","percent":"4.23","return":"-64.98"},{"company":"MetroPCS Communications, Inc. C","symbol":"PCS","percent":"4.15","return":"32.72"},{"company":"United States Cellular Corporat","symbol":"USM","percent":"1.13","return":"-10.82"},{"company":"Leap Wireless International, In","symbol":"LEAP","percent":"0.61","return":"-24.65"}]