[{"company":"Varian Medical Systems, Inc. Co","symbol":"VAR","percent":"2.99","return":"-9.92"},{"company":"CarMax Inc","symbol":"KMX","percent":"2.66","return":"-6.76"},{"company":"Pall Corporation Common Stock","symbol":"PLL","percent":"2.42","return":"13.68"},{"company":"Wyndham Worldwide Corp Common","symbol":"WYN","percent":"2.31","return":"41.58"},{"company":"Vantiv, Inc. Class A Common Sto","symbol":"VNTV","percent":"2.30","return":"-7.32"},{"company":"Microchip Technology Incorporat","symbol":"MCHP","percent":"2.29","return":"20.44"},{"company":"Northern Trust Corporation","symbol":"NTRS","percent":"2.27","return":"57.25"},{"company":"Fortune Brands Home & Security,","symbol":"FBHS","percent":"2.18","return":"3.47"},{"company":"Fastenal Company","symbol":"FAST","percent":"2.18","return":"-17.84"},{"company":"Polypore International Inc Comm","symbol":"PPO","percent":"2.16","return":"N/A"}]